{
  "_comment": [
    "キャラクター(ペルソナ)の定義ファイル。server.js が起動時に読み込みます。",
    "各要素: id / name / color(#RRGGBB) / desc。",
    "id は行動ポリシーモデル data/persona_<id>.onnx と対応します。",
    "  → 対応する .onnx があれば学習済みの挙動、無ければランダム移動にフォールバック。",
    "キャラクター数(NUM_AGENTS, 1-50)がペルソナ数より多い場合は、この一覧を順番に割り当てて繰り返します。",
    "この _comment キーは無視されます。"
  ],
  "personas": [
    { "id": "A", "name": "Explorer Rex",     "color": "#ff3355", "desc": "Actively explores new areas" },
    { "id": "B", "name": "Homebody Lily",    "color": "#00ccff", "desc": "Takes the shortest route" },
    { "id": "C", "name": "Social Marco",     "color": "#33ff88", "desc": "Gathers near others" },
    { "id": "D", "name": "Businessman Cole", "color": "#ffee00", "desc": "Moves straight, efficiency first" },
    { "id": "E", "name": "Tourist Elena",    "color": "#ff7700", "desc": "Wanders around buildings" }
  ]
}
